sqlite_web/.DS_Store
sqlite_web/__init__.py
sqlite_web/__main__.py
sqlite_web/sqlite_web.py
sqlite_web/static/.DS_Store
sqlite_web/static/css/bootstrap.min.css
sqlite_web/static/css/jquery.dataTables.min.css
sqlite_web/static/css/responsive.bootstrap.min.css
sqlite_web/static/css/sqlbrowse.css
sqlite_web/static/css/syntax-highlight.css
sqlite_web/static/fa/LICENSE.txt
sqlite_web/static/fa/css/all.css
sqlite_web/static/fa/css/all.min.css
sqlite_web/static/fa/css/brands.css
sqlite_web/static/fa/css/brands.min.css
sqlite_web/static/fa/css/fontawesome.css
sqlite_web/static/fa/css/fontawesome.min.css
sqlite_web/static/fa/css/regular.css
sqlite_web/static/fa/css/regular.min.css
sqlite_web/static/fa/css/solid.css
sqlite_web/static/fa/css/solid.min.css
sqlite_web/static/fa/css/svg-with-js.css
sqlite_web/static/fa/css/svg-with-js.min.css
sqlite_web/static/fa/css/v4-shims.css
sqlite_web/static/fa/css/v4-shims.min.css
sqlite_web/static/fa/js/all.js
sqlite_web/static/fa/js/all.min.js
sqlite_web/static/fa/js/brands.js
sqlite_web/static/fa/js/brands.min.js
sqlite_web/static/fa/js/conflict-detection.js
sqlite_web/static/fa/js/conflict-detection.min.js
sqlite_web/static/fa/js/fontawesome.js
sqlite_web/static/fa/js/fontawesome.min.js
sqlite_web/static/fa/js/regular.js
sqlite_web/static/fa/js/regular.min.js
sqlite_web/static/fa/js/solid.js
sqlite_web/static/fa/js/solid.min.js
sqlite_web/static/fa/js/v4-shims.js
sqlite_web/static/fa/js/v4-shims.min.js
sqlite_web/static/fa/less/_animated.less
sqlite_web/static/fa/less/_bordered-pulled.less
sqlite_web/static/fa/less/_core.less
sqlite_web/static/fa/less/_fixed-width.less
sqlite_web/static/fa/less/_icons.less
sqlite_web/static/fa/less/_larger.less
sqlite_web/static/fa/less/_list.less
sqlite_web/static/fa/less/_mixins.less
sqlite_web/static/fa/less/_rotated-flipped.less
sqlite_web/static/fa/less/_screen-reader.less
sqlite_web/static/fa/less/_shims.less
sqlite_web/static/fa/less/_stacked.less
sqlite_web/static/fa/less/_variables.less
sqlite_web_jmalabanan-0.0.11.dist-info/LICENSE
sqlite_web_jmalabanan-0.0.11.dist-info/METADATA
sqlite_web_jmalabanan-0.0.11.dist-info/WHEEL
sqlite_web_jmalabanan-0.0.11.dist-info/entry_points.txt
sqlite_web_jmalabanan-0.0.11.dist-info/top_level.txt
sqlite_web_jmalabanan-0.0.11.dist-info/RECORD
